package ClassSub;

import javax.swing.*;
import java.awt.*;

class Class98 extends JFrame
{
    
    
    public Class98(final String s) {
        // 
        // This method could not be decompiled.
        // 
        // Original Bytecode:
        // 
        //     3: athrow         
        //     4: aload_0        
        //     5: invokespecial   javax/swing/JFrame.<init>:()V
        //     8: new             Ljavax/swing/JLabel;
        //    11: dup            
        //    12: aload_1        
        //    13: invokespecial   javax/swing/JLabel.<init>:(Ljava/lang/String;)V
        //    16: astore_2       
        //    17: new             Ljava/awt/Button;
        //    20: dup            
        //    21: new             Ljava/lang/StringBuilder;
        //    24: dup            
        //    25: invokespecial   java/lang/StringBuilder.<init>:()V
        //    28: aload_1        
        //    29: invokevirtual   java/lang/StringBuilder.append:(Ljava/lang/String;)Ljava/lang/StringBuilder;
        //    32: ldc             "\u786e\u5b9a"
        //    34: invokevirtual   java/lang/StringBuilder.append:(Ljava/lang/String;)Ljava/lang/StringBuilder;
        //    37: invokevirtual   java/lang/StringBuilder.toString:()Ljava/lang/String;
        //    40: invokespecial   java/awt/Button.<init>:(Ljava/lang/String;)V
        //    43: astore_3       
        //    44: aload_3        
        //    45: new             LClassSub/Class73;
        //    48: dup            
        //    49: aload_0        
        //    50: aload_1        
        //    51: invokespecial   ClassSub/Class73.<init>:(LClassSub/Class98;Ljava/lang/String;)V
        //    54: invokevirtual   java/awt/Button.addActionListener:(Ljava/awt/event/ActionListener;)V
        //    57: aload_0        
        //    58: aload_2        
        //    59: invokevirtual   ClassSub/Class98.add:(Ljava/awt/Component;)Ljava/awt/Component;
        //    62: pop            
        //    63: aload_0        
        //    64: aload_3        
        //    65: invokevirtual   ClassSub/Class98.add:(Ljava/awt/Component;)Ljava/awt/Component;
        //    68: pop            
        //    69: aload_0        
        //    70: new             Ljava/awt/FlowLayout;
        //    73: dup            
        //    74: invokespecial   java/awt/FlowLayout.<init>:()V
        //    77: invokevirtual   ClassSub/Class98.setLayout:(Ljava/awt/LayoutManager;)V
        //    80: aload_0        
        //    81: ldc             "\u63d0\u793a"
        //    83: invokevirtual   ClassSub/Class98.setTitle:(Ljava/lang/String;)V
        //    86: aload_0        
        //    87: ldc             300
        //    89: ldc             80
        //    91: invokevirtual   ClassSub/Class98.setSize:(II)V
        //    94: aload_0        
        //    95: aconst_null    
        //    96: invokevirtual   ClassSub/Class98.setLocationRelativeTo:(Ljava/awt/Component;)V
        //    99: aload_0        
        //   100: ldc             1
        //   102: invokevirtual   ClassSub/Class98.setAlwaysOnTop:(Z)V
        //   105: aload_0        
        //   106: ldc             0
        //   108: invokevirtual   ClassSub/Class98.setResizable:(Z)V
        //   111: aload_0        
        //   112: ldc             1
        //   114: invokevirtual   ClassSub/Class98.setVisible:(Z)V
        //   117: return         
        //   118: nop            
        //   119: nop            
        //   120: nop            
        //   121: nop            
        //   122: athrow         
        // 
        // The error that occurred was:
        // 
        // java.lang.NullPointerException
        // 
        throw new IllegalStateException("An error occurred while decompiling this method.");
    }
}
